carbs/__init__.py
carbs/guidance.py
carbs/swarm_estimator/__init__.py
carbs/swarm_estimator/slam.py
carbs/swarm_estimator/tracker.py
carbs/utilities/__init__.py
carbs/utilities/graphs.py
carbs/utilities/graphs_subroutines.py
carbs/utilities/sampling.py
carbs-1.0.4.dist-info/LICENSE
carbs-1.0.4.dist-info/METADATA
carbs-1.0.4.dist-info/WHEEL
carbs-1.0.4.dist-info/top_level.txt
carbs-1.0.4.dist-info/RECORD
