Metadata-Version: 2.1
Name: carbs
Version: 1.0.4
Summary: A package for Guidance, Navigation, and Control (GNC) for Autonomous Swarms Using Random finite sets (RFS).
Author: Laboratory for Autonomy GNC and Estimation Research (LAGER)
License: MIT License
Project-URL: homepage, http://lager.ua.edu/
Project-URL: documentation, https://drjdlarson.github.io/carbs/
Project-URL: repository, https://github.com/drjdlarson/carbs
Keywords: Guidance Navigation and Control,multi-vehicle teams,Random Finite Sets,multi-object tracking
Classifier: Intended Audience :: Developers
Classifier: Intended Audience :: Education
Classifier: Intended Audience :: Science/Research
Classifier: Programming Language :: Python
Classifier: Programming Language :: Python :: 3.7
Classifier: Programming Language :: Python :: 3.8
Classifier: Programming Language :: Python :: 3.9
Classifier: Topic :: Scientific/Engineering
Classifier: Operating System :: POSIX :: Linux
Requires-Python: <3.10,>=3.7
License-File: LICENSE
Requires-Dist: serums
Requires-Dist: gncpy
Requires-Dist: numpy
Requires-Dist: scipy
Requires-Dist: matplotlib
